Metadata-Version: 2.1
Name: Qzec
Version: 0.0.1
Summary: Simple Chrome thing
Home-page: 
Author: SIRQ
Author-email: sr.pentesters@gmail.com
License: MIT
Keywords: Qzec
Classifier: Development Status :: 5 - Production/Stable
Classifier: Intended Audience :: Education
Classifier: Operating System :: Microsoft :: Windows :: Windows 10
Classifier: License :: OSI Approved :: MIT License
Classifier: Programming Language :: Python :: 3
License-File: LICENCE.txt
